pybode/__init__.py
pybode/pybode.py
pybode-0.0.1.dist-info/LICENSE
pybode-0.0.1.dist-info/METADATA
pybode-0.0.1.dist-info/WHEEL
pybode-0.0.1.dist-info/top_level.txt
pybode-0.0.1.dist-info/RECORD
