Metadata-Version: 2.1
Name: pybode
Version: 0.0.1
Summary: Support package for Bode diagramms
Home-page: https://github.com/PMSchueler/pybode
Author: P.M.Schueler
Author-email: peter.schueler@gmxpro.de
Classifier: Programming Language :: Python :: 3
Classifier: License :: OSI Approved :: MIT License
Classifier: Operating System :: OS Independent
Requires-Python: >=3.11
License-File: LICENSE
Requires-Dist: pylabdevs-tspspi >=0.0.15
Requires-Dist: pydho800 >=0.0.9
Requires-Dist: pydg1000z >=0.1.0
Requires-Dist: numpy >=1.26.3
Requires-Dist: scipy >=1.11.4
Requires-Dist: matplotlib >=3.8.2
